[
  {
    "pos": 5,
    "z": -388,
    "x": 356
  },
  {
    "pos": 8,
    "z": -215,
    "x": 358
  },
  {
    "pos": 9,
    "z": -217,
    "x": 378
  },
  {
    "pos": 10,
    "z": -150,
    "x": 315
  },
  {
    "pos": 11,
    "z": -258,
    "x": 358
  },
  {
    "pos": 12,
    "z": -263,
    "x": 356
  },
  {
    "pos": 14,
    "z": -292,
    "x": 489
  },
  {
    "pos": 15,
    "z": -314,
    "x": 552
  },
  {
    "pos": 16,
    "z": -330,
    "x": 654
  },
  {
    "pos": 17,
    "z": -331,
    "x": 657
  },
  {
    "pos": 18,
    "z": -360,
    "x": 840
  },
  {
    "pos": 19,
    "z": -365,
    "x": 916
  },
  {
    "pos": 20,
    "z": -357,
    "x": 1018
  },
  {
    "pos": 21,
    "z": -341,
    "x": 1080
  },
  {
    "pos": 22,
    "z": -326,
    "x": 1165
  },
  {
    "pos": 23,
    "z": -350,
    "x": 1173
  },
  {
    "pos": 24,
    "z": -290,
    "x": 1185
  },
  {
    "pos": 25,
    "z": -287,
    "x": 1250
  },
  {
    "pos": 26,
    "z": -275,
    "x": 1233
  },
  {
    "pos": 27,
    "z": -260,
    "x": 1216
  },
  {
    "pos": 28,
    "z": -263,
    "x": 1208
  },
  {
    "pos": 48,
    "z": -226,
    "x": 368
  },
  {
    "pos": 49,
    "z": -156,
    "x": 373
  },
  {
    "pos": 50,
    "z": -225,
    "x": 474
  },
  {
    "pos": 51,
    "z": -255,
    "x": 530
  },
  {
    "pos": 52,
    "z": -301,
    "x": 625
  },
  {
    "pos": 53,
    "z": -315,
    "x": 711
  },
  {
    "pos": 54,
    "z": -215,
    "x": 770
  },
  {
    "pos": 55,
    "z": -300,
    "x": 906
  },
  {
    "pos": 56,
    "z": -299,
    "x": 983
  },
  {
    "pos": 57,
    "z": -236,
    "x": 1097
  },
  {
    "pos": 58,
    "z": -260,
    "x": 1098
  },
  {
    "pos": 59,
    "z": -294,
    "x": 1190
  },
  {
    "pos": 61,
    "z": -197,
    "x": 1205
  },
  {
    "pos": 68,
    "z": -67,
    "x": 957
  },
  {
    "pos": 69,
    "z": -70,
    "x": 958
  },
  {
    "pos": 70,
    "z": -3,
    "x": 864
  },
  {
    "pos": 82,
    "z": -141,
    "x": 398
  },
  {
    "pos": 83,
    "z": -187,
    "x": 442
  },
  {
    "pos": 84,
    "z": -181,
    "x": 470
  },
  {
    "pos": 85,
    "z": -180,
    "x": 545
  },
  {
    "pos": 86,
    "z": -208,
    "x": 549
  },
  {
    "pos": 87,
    "z": -210,
    "x": 706
  },
  {
    "pos": 88,
    "z": -193,
    "x": 818
  },
  {
    "pos": 89,
    "z": -218,
    "x": 907
  },
  {
    "pos": 90,
    "z": -196,
    "x": 987
  },
  {
    "pos": 91,
    "z": -193,
    "x": 1076
  },
  {
    "pos": 92,
    "z": -169,
    "x": 1121
  },
  {
    "pos": 95,
    "z": -111,
    "x": 1205
  },
  {
    "pos": 102,
    "z": -6,
    "x": 848
  },
  {
    "pos": 105,
    "z": -18,
    "x": 657
  },
  {
    "pos": 106,
    "z": -9,
    "x": 644
  },
  {
    "pos": 112,
    "z": -13,
    "x": 377
  },
  {
    "pos": 113,
    "z": -41,
    "x": 408
  },
  {
    "pos": 114,
    "z": -61,
    "x": 425
  },
  {
    "pos": 115,
    "z": -64,
    "x": 490
  },
  {
    "pos": 116,
    "z": -83,
    "x": 483
  },
  {
    "pos": 117,
    "z": -70,
    "x": 579
  },
  {
    "pos": 118,
    "z": -109,
    "x": 675
  },
  {
    "pos": 119,
    "z": -74,
    "x": 773
  },
  {
    "pos": 120,
    "z": -101,
    "x": 792
  },
  {
    "pos": 121,
    "z": -84,
    "x": 941
  },
  {
    "pos": 122,
    "z": 22,
    "x": 1029
  },
  {
    "pos": 123,
    "z": -19,
    "x": 1113
  },
  {
    "pos": 124,
    "z": -60,
    "x": 1133
  },
  {
    "pos": 125,
    "z": -21,
    "x": 1134
  },
  {
    "pos": 126,
    "z": 8,
    "x": 1196
  },
  {
    "pos": 129,
    "z": -18,
    "x": 1110
  },
  {
    "pos": 145,
    "z": 31,
    "x": 404
  },
  {
    "pos": 146,
    "z": 30,
    "x": 517
  },
  {
    "pos": 147,
    "z": 26,
    "x": 453
  },
  {
    "pos": 148,
    "z": 9,
    "x": 519
  },
  {
    "pos": 149,
    "z": 29,
    "x": 560
  },
  {
    "pos": 150,
    "z": 3,
    "x": 773
  },
  {
    "pos": 151,
    "z": 6,
    "x": 848
  },
  {
    "pos": 152,
    "z": 41,
    "x": 952
  },
  {
    "pos": 153,
    "z": 22,
    "x": 971
  },
  {
    "pos": 154,
    "z": 52,
    "x": 1098
  },
  {
    "pos": 155,
    "z": 12,
    "x": 1068
  },
  {
    "pos": 156,
    "z": 46,
    "x": 1087
  },
  {
    "pos": 166,
    "z": 71,
    "x": 758
  },
  {
    "pos": 173,
    "z": 93,
    "x": 406
  },
  {
    "pos": 175,
    "z": 95,
    "x": 421
  },
  {
    "pos": 176,
    "z": 103,
    "x": 498
  },
  {
    "pos": 177,
    "z": 102,
    "x": 502
  },
  {
    "pos": 178,
    "z": 94,
    "x": 596
  },
  {
    "pos": 179,
    "z": 90,
    "x": 593
  },
  {
    "pos": 180,
    "z": 109,
    "x": 757
  },
  {
    "pos": 181,
    "z": 102,
    "x": 847
  },
  {
    "pos": 182,
    "z": 100,
    "x": 917
  },
  {
    "pos": 183,
    "z": 94,
    "x": 916
  },
  {
    "pos": 184,
    "z": 104,
    "x": 1061
  },
  {
    "pos": 185,
    "z": 123,
    "x": 1110
  },
  {
    "pos": 186,
    "z": 120,
    "x": 1109
  },
  {
    "pos": 187,
    "z": 73,
    "x": 1097
  },
  {
    "pos": 188,
    "z": 133,
    "x": 1106
  },
  {
    "pos": 192,
    "z": 169,
    "x": 938
  },
  {
    "pos": 196,
    "z": 123,
    "x": 735
  },
  {
    "pos": 198,
    "z": 162,
    "x": 623
  },
  {
    "pos": 200,
    "z": 237,
    "x": 476
  },
  {
    "pos": 203,
    "z": 153,
    "x": 477
  },
  {
    "pos": 204,
    "z": 144,
    "x": 534
  },
  {
    "pos": 205,
    "z": 198,
    "x": 666
  },
  {
    "pos": 206,
    "z": 136,
    "x": 598
  },
  {
    "pos": 207,
    "z": 142,
    "x": 660
  },
  {
    "pos": 208,
    "z": 155,
    "x": 767
  },
  {
    "pos": 209,
    "z": 98,
    "x": 852
  },
  {
    "pos": 210,
    "z": 164,
    "x": 898
  },
  {
    "pos": 212,
    "z": 158,
    "x": 1000
  },
  {
    "pos": 213,
    "z": 172,
    "x": 1020
  },
  {
    "pos": 214,
    "z": 169,
    "x": 1023
  },
  {
    "pos": 215,
    "z": 256,
    "x": 1066
  },
  {
    "pos": 217,
    "z": 193,
    "x": 968
  },
  {
    "pos": 218,
    "z": 191,
    "x": 969
  },
  {
    "pos": 220,
    "z": 183,
    "x": 860
  },
  {
    "pos": 223,
    "z": 199,
    "x": 653
  },
  {
    "pos": 225,
    "z": 221,
    "x": 543
  },
  {
    "pos": 227,
    "z": 169,
    "x": 548
  },
  {
    "pos": 228,
    "z": 191,
    "x": 480
  },
  {
    "pos": 229,
    "z": 164,
    "x": 566
  },
  {
    "pos": 230,
    "z": 141,
    "x": 592
  },
  {
    "pos": 231,
    "z": 200,
    "x": 664
  },
  {
    "pos": 232,
    "z": 262,
    "x": 733
  },
  {
    "pos": 233,
    "z": 212,
    "x": 833
  },
  {
    "pos": 234,
    "z": 236,
    "x": 924
  },
  {
    "pos": 235,
    "z": 221,
    "x": 946
  },
  {
    "pos": 236,
    "z": 229,
    "x": 999
  },
  {
    "pos": 237,
    "z": 246,
    "x": 1027
  },
  {
    "pos": 238,
    "z": 241,
    "x": 1009
  },
  {
    "pos": 239,
    "z": 277,
    "x": 1079
  },
  {
    "pos": 240,
    "z": 259,
    "x": 1082
  },
  {
    "pos": 243,
    "z": 201,
    "x": 904
  },
  {
    "pos": 247,
    "z": 212,
    "x": 685
  },
  {
    "pos": 249,
    "z": 238,
    "x": 597
  },
  {
    "pos": 250,
    "z": 186,
    "x": 451
  },
  {
    "pos": 251,
    "z": 287,
    "x": 464
  },
  {
    "pos": 252,
    "z": 236,
    "x": 552
  },
  {
    "pos": 253,
    "z": 239,
    "x": 571
  },
  {
    "pos": 254,
    "z": 298,
    "x": 500
  },
  {
    "pos": 255,
    "z": 304,
    "x": 670
  },
  {
    "pos": 256,
    "z": 289,
    "x": 769
  },
  {
    "pos": 257,
    "z": 213,
    "x": 836
  },
  {
    "pos": 258,
    "z": 276,
    "x": 890
  },
  {
    "pos": 259,
    "z": 193,
    "x": 974
  },
  {
    "pos": 260,
    "z": 252,
    "x": 1016
  },
  {
    "pos": 261,
    "z": 138,
    "x": 1030
  },
  {
    "pos": 262,
    "z": 286,
    "x": 1065
  },
  {
    "pos": 264,
    "z": 306,
    "x": 916
  },
  {
    "pos": 270,
    "z": 341,
    "x": 509
  },
  {
    "pos": 272,
    "z": 270,
    "x": 551
  },
  {
    "pos": 273,
    "z": 287,
    "x": 521
  },
  {
    "pos": 274,
    "z": 233,
    "x": 571
  },
  {
    "pos": 275,
    "z": 395,
    "x": 662
  },
  {
    "pos": 276,
    "z": 331,
    "x": 719
  },
  {
    "pos": 277,
    "z": 314,
    "x": 723
  },
  {
    "pos": 279,
    "z": 311,
    "x": 937
  },
  {
    "pos": 281,
    "z": 334,
    "x": 1025
  },
  {
    "pos": 282,
    "z": 332,
    "x": 1078
  },
  {
    "pos": 283,
    "z": 328,
    "x": 1079
  },
  {
    "pos": 285,
    "z": 344,
    "x": 932
  },
  {
    "pos": 286,
    "z": 343,
    "x": 933
  },
  {
    "pos": 290,
    "z": 328,
    "x": 680
  },
  {
    "pos": 293,
    "z": 341,
    "x": 509
  },
  {
    "pos": 294,
    "z": 349,
    "x": 506
  },
  {
    "pos": 295,
    "z": 340,
    "x": 586
  },
  {
    "pos": 296,
    "z": 253,
    "x": 550
  },
  {
    "pos": 297,
    "z": 348,
    "x": 583
  },
  {
    "pos": 298,
    "z": 350,
    "x": 665
  },
  {
    "pos": 299,
    "z": 362,
    "x": 735
  },
  {
    "pos": 300,
    "z": 367,
    "x": 899
  },
  {
    "pos": 301,
    "z": 373,
    "x": 920
  },
  {
    "pos": 302,
    "z": 345,
    "x": 975
  },
  {
    "pos": 303,
    "z": 359,
    "x": 1069
  },
  {
    "pos": 305,
    "z": 379,
    "x": 1068
  },
  {
    "pos": 306,
    "z": 369,
    "x": 1065
  },
  {
    "pos": 312,
    "z": 415,
    "x": 723
  },
  {
    "pos": 313,
    "z": 327,
    "x": 690
  },
  {
    "pos": 314,
    "z": 417,
    "x": 632
  },
  {
    "pos": 315,
    "z": 432,
    "x": 552
  },
  {
    "pos": 316,
    "z": 458,
    "x": 559
  },
  {
    "pos": 317,
    "z": 460,
    "x": 534
  },
  {
    "pos": 318,
    "z": 477,
    "x": 527
  },
  {
    "pos": 319,
    "z": 474,
    "x": 574
  },
  {
    "pos": 320,
    "z": 490,
    "x": 597
  },
  {
    "pos": 321,
    "z": 479,
    "x": 686
  },
  {
    "pos": 322,
    "z": 478,
    "x": 753
  },
  {
    "pos": 323,
    "z": 468,
    "x": 749
  },
  {
    "pos": 324,
    "z": 424,
    "x": 897
  },
  {
    "pos": 325,
    "z": 351,
    "x": 976
  },
  {
    "pos": 326,
    "z": 425,
    "x": 942
  },
  {
    "pos": 327,
    "z": 415,
    "x": 995
  },
  {
    "pos": 335,
    "z": 424,
    "x": 687
  },
  {
    "pos": 338,
    "z": 429,
    "x": 498
  },
  {
    "pos": 339,
    "z": 428,
    "x": 499
  },
  {
    "pos": 340,
    "z": 512,
    "x": 543
  },
  {
    "pos": 341,
    "z": 558,
    "x": 621
  },
  {
    "pos": 342,
    "z": 467,
    "x": 575
  },
  {
    "pos": 344,
    "z": 511,
    "x": 701
  },
  {
    "pos": 345,
    "z": 540,
    "x": 782
  },
  {
    "pos": 346,
    "z": 582,
    "x": 804
  },
  {
    "pos": 347,
    "z": 545,
    "x": 936
  },
  {
    "pos": 348,
    "z": 491,
    "x": 980
  },
  {
    "pos": 349,
    "z": 543,
    "x": 1065
  },
  {
    "pos": 353,
    "z": 554,
    "x": 823
  },
  {
    "pos": 354,
    "z": 548,
    "x": 825
  },
  {
    "pos": 356,
    "z": 517,
    "x": 666
  },
  {
    "pos": 360,
    "z": 607,
    "x": 501
  },
  {
    "pos": 361,
    "z": 533,
    "x": 551
  },
  {
    "pos": 362,
    "z": 543,
    "x": 611
  },
  {
    "pos": 363,
    "z": 608,
    "x": 620
  },
  {
    "pos": 364,
    "z": 557,
    "x": 742
  },
  {
    "pos": 365,
    "z": 587,
    "x": 816
  },
  {
    "pos": 366,
    "z": 622,
    "x": 915
  },
  {
    "pos": 367,
    "z": 581,
    "x": 914
  },
  {
    "pos": 368,
    "z": 568,
    "x": 914
  },
  {
    "pos": 370,
    "z": 607,
    "x": 1030
  },
  {
    "pos": 374,
    "z": 545,
    "x": 833
  },
  {
    "pos": 380,
    "z": 528,
    "x": 568
  },
  {
    "pos": 381,
    "z": 532,
    "x": 551
  },
  {
    "pos": 382,
    "z": 546,
    "x": 504
  },
  {
    "pos": 383,
    "z": 678,
    "x": 644
  },
  {
    "pos": 384,
    "z": 672,
    "x": 661
  },
  {
    "pos": 385,
    "z": 616,
    "x": 813
  },
  {
    "pos": 386,
    "z": 616,
    "x": 902
  },
  {
    "pos": 387,
    "z": 583,
    "x": 904
  },
  {
    "pos": 388,
    "z": 632,
    "x": 971
  },
  {
    "pos": 393,
    "z": 599,
    "x": 792
  },
  {
    "pos": 398,
    "z": 621,
    "x": 574
  },
  {
    "pos": 399,
    "z": 620,
    "x": 575
  },
  {
    "pos": 400,
    "z": 721,
    "x": 676
  },
  {
    "pos": 401,
    "z": 731,
    "x": 680
  },
  {
    "pos": 402,
    "z": 679,
    "x": 762
  },
  {
    "pos": 403,
    "z": 676,
    "x": 839
  },
  {
    "pos": 404,
    "z": 695,
    "x": 901
  },
  {
    "pos": 405,
    "z": 691,
    "x": 968
  },
  {
    "pos": 406,
    "z": 681,
    "x": 990
  },
  {
    "pos": 407,
    "z": 664,
    "x": 987
  },
  {
    "pos": 410,
    "z": 581,
    "x": 793
  },
  {
    "pos": 411,
    "z": 622,
    "x": 744
  },
  {
    "pos": 415,
    "z": 715,
    "x": 566
  },
  {
    "pos": 416,
    "z": 706,
    "x": 583
  },
  {
    "pos": 417,
    "z": 722,
    "x": 630
  },
  {
    "pos": 418,
    "z": 744,
    "x": 682
  },
  {
    "pos": 419,
    "z": 735,
    "x": 687
  },
  {
    "pos": 420,
    "z": 701,
    "x": 818
  },
  {
    "pos": 421,
    "z": 761,
    "x": 937
  },
  {
    "pos": 425,
    "z": 702,
    "x": 801
  },
  {
    "pos": 429,
    "z": 703,
    "x": 569
  },
  {
    "pos": 431,
    "z": 732,
    "x": 649
  },
  {
    "pos": 432,
    "z": 748,
    "x": 701
  },
  {
    "pos": 433,
    "z": 776,
    "x": 782
  },
  {
    "pos": 434,
    "z": 797,
    "x": 840
  },
  {
    "pos": 435,
    "z": 781,
    "x": 887
  },
  {
    "pos": 436,
    "z": 775,
    "x": 886
  },
  {
    "pos": 441,
    "z": 755,
    "x": 747
  },
  {
    "pos": 444,
    "z": 858,
    "x": 565
  },
  {
    "pos": 446,
    "z": 831,
    "x": 648
  },
  {
    "pos": 447,
    "z": 883,
    "x": 635
  },
  {
    "pos": 448,
    "z": 862,
    "x": 734
  },
  {
    "pos": 449,
    "z": 927,
    "x": 775
  },
  {
    "pos": 450,
    "z": 880,
    "x": 912
  },
  {
    "pos": 451,
    "z": 868,
    "x": 914
  },
  {
    "pos": 457,
    "z": 867,
    "x": 603
  },
  {
    "pos": 458,
    "z": 947,
    "x": 591
  },
  {
    "pos": 459,
    "z": 892,
    "x": 661
  },
  {
    "pos": 460,
    "z": 940,
    "x": 698
  },
  {
    "pos": 461,
    "z": 897,
    "x": 774
  },
  {
    "pos": 462,
    "z": 949,
    "x": 887
  },
  {
    "pos": 463,
    "z": 919,
    "x": 837
  },
  {
    "pos": 464,
    "z": 965,
    "x": 944
  },
  {
    "pos": 465,
    "z": 923,
    "x": 909
  },
  {
    "pos": 466,
    "z": 920,
    "x": 906
  },
  {
    "pos": 468,
    "z": 901,
    "x": 755
  },
  {
    "pos": 471,
    "z": 974,
    "x": 641
  },
  {
    "pos": 472,
    "z": 1028,
    "x": 677
  },
  {
    "pos": 473,
    "z": 1040,
    "x": 784
  },
  {
    "pos": 474,
    "z": 1068,
    "x": 841
  },
  {
    "pos": 475,
    "z": 1013,
    "x": 855
  },
  {
    "pos": 476,
    "z": 1021,
    "x": 933
  },
  {
    "pos": 477,
    "z": 1021,
    "x": 928
  },
  {
    "pos": 482,
    "z": 1092,
    "x": 698
  },
  {
    "pos": 483,
    "z": 1017,
    "x": 634
  },
  {
    "pos": 484,
    "z": 1097,
    "x": 628
  },
  {
    "pos": 485,
    "z": 1157,
    "x": 739
  },
  {
    "pos": 486,
    "z": 1162,
    "x": 797
  },
  {
    "pos": 487,
    "z": 1143,
    "x": 855
  },
  {
    "pos": 488,
    "z": 1090,
    "x": 910
  },
  {
    "pos": 491,
    "z": 1057,
    "x": 723
  },
  {
    "pos": 492,
    "z": 1094,
    "x": 681
  },
  {
    "pos": 493,
    "z": 1150,
    "x": 677
  },
  {
    "pos": 494,
    "z": 1248,
    "x": 701
  },
  {
    "pos": 495,
    "z": 1251,
    "x": 790
  },
  {
    "pos": 496,
    "z": 1250,
    "x": 846
  },
  {
    "pos": 497,
    "z": 1198,
    "x": 781
  },
  {
    "pos": 498,
    "z": 1187,
    "x": 779
  },
  {
    "pos": 8,
    "z": -101,
    "y": 704
  },
  {
    "pos": 18,
    "z": -228,
    "y": 296
  },
  {
    "pos": 19,
    "z": -265,
    "y": 364
  },
  {
    "pos": 20,
    "z": -294,
    "y": 358
  },
  {
    "pos": 21,
    "z": -365,
    "y": 435
  },
  {
    "pos": 22,
    "z": -324,
    "y": 431
  },
  {
    "pos": 23,
    "z": -376,
    "y": 502
  },
  {
    "pos": 24,
    "z": -363,
    "y": 618
  },
  {
    "pos": 25,
    "z": -391,
    "y": 665
  },
  {
    "pos": 26,
    "z": -399,
    "y": 655
  },
  {
    "pos": 27,
    "z": -414,
    "y": 814
  },
  {
    "pos": 28,
    "z": -421,
    "y": 913
  },
  {
    "pos": 29,
    "z": -407,
    "y": 995
  },
  {
    "pos": 30,
    "z": -408,
    "y": 1058
  },
  {
    "pos": 31,
    "z": -386,
    "y": 1155
  },
  {
    "pos": 32,
    "z": -331,
    "y": 1163
  },
  {
    "pos": 33,
    "z": -266,
    "y": 1183
  },
  {
    "pos": 34,
    "z": -156,
    "y": 1262
  },
  {
    "pos": 35,
    "z": -235,
    "y": 1211
  },
  {
    "pos": 42,
    "z": -100,
    "y": 1000
  },
  {
    "pos": 55,
    "z": -181,
    "y": 350
  },
  {
    "pos": 57,
    "z": -216,
    "y": 378
  },
  {
    "pos": 58,
    "z": -309,
    "y": 557
  },
  {
    "pos": 59,
    "z": -289,
    "y": 550
  },
  {
    "pos": 61,
    "z": -302,
    "y": 728
  },
  {
    "pos": 62,
    "z": -342,
    "y": 832
  },
  {
    "pos": 63,
    "z": -333,
    "y": 912
  },
  {
    "pos": 64,
    "z": -332,
    "y": 991
  },
  {
    "pos": 65,
    "z": -257,
    "y": 1111
  },
  {
    "pos": 66,
    "z": -259,
    "y": 1140
  },
  {
    "pos": 67,
    "z": -177,
    "y": 1158
  },
  {
    "pos": 68,
    "z": -180,
    "y": 1159
  },
  {
    "pos": 70,
    "z": -107,
    "y": 1182
  },
  {
    "pos": 74,
    "z": -53,
    "y": 1049
  },
  {
    "pos": 77,
    "z": -56,
    "y": 869
  },
  {
    "pos": 81,
    "z": -20,
    "y": 653
  },
  {
    "pos": 90,
    "z": -163,
    "y": 417
  },
  {
    "pos": 91,
    "z": -169,
    "y": 426
  },
  {
    "pos": 92,
    "z": -173,
    "y": 500
  },
  {
    "pos": 93,
    "z": -190,
    "y": 588
  },
  {
    "pos": 94,
    "z": -198,
    "y": 677
  },
  {
    "pos": 95,
    "z": -182,
    "y": 764
  },
  {
    "pos": 96,
    "z": -218,
    "y": 887
  },
  {
    "pos": 97,
    "z": -202,
    "y": 959
  },
  {
    "pos": 98,
    "z": -220,
    "y": 1079
  },
  {
    "pos": 99,
    "z": -148,
    "y": 1103
  },
  {
    "pos": 100,
    "z": -142,
    "y": 1108
  },
  {
    "pos": 103,
    "z": -74,
    "y": 1148
  },
  {
    "pos": 104,
    "z": -8,
    "y": 1164
  },
  {
    "pos": 111,
    "z": 43,
    "y": 757
  },
  {
    "pos": 115,
    "z": 39,
    "y": 559
  },
  {
    "pos": 119,
    "z": 26,
    "y": 378
  },
  {
    "pos": 120,
    "z": -14,
    "y": 420
  },
  {
    "pos": 122,
    "z": 31,
    "y": 464
  },
  {
    "pos": 123,
    "z": -2,
    "y": 467
  },
  {
    "pos": 124,
    "z": -61,
    "y": 558
  },
  {
    "pos": 125,
    "z": -65,
    "y": 640
  },
  {
    "pos": 126,
    "z": -28,
    "y": 693
  },
  {
    "pos": 127,
    "z": -67,
    "y": 808
  },
  {
    "pos": 128,
    "z": -92,
    "y": 815
  },
  {
    "pos": 129,
    "z": -63,
    "y": 980
  },
  {
    "pos": 130,
    "z": -49,
    "y": 1054
  },
  {
    "pos": 131,
    "z": -49,
    "y": 1141
  },
  {
    "pos": 132,
    "z": -39,
    "y": 1165
  },
  {
    "pos": 134,
    "z": 33,
    "y": 1144
  },
  {
    "pos": 135,
    "z": 43,
    "y": 1149
  },
  {
    "pos": 136,
    "z": 63,
    "y": 1092
  },
  {
    "pos": 150,
    "z": 76,
    "y": 408
  },
  {
    "pos": 151,
    "z": 67,
    "y": 416
  },
  {
    "pos": 152,
    "z": 59,
    "y": 420
  },
  {
    "pos": 153,
    "z": 41,
    "y": 492
  },
  {
    "pos": 154,
    "z": 34,
    "y": 502
  },
  {
    "pos": 155,
    "z": 15,
    "y": 584
  },
  {
    "pos": 156,
    "z": -64,
    "y": 668
  },
  {
    "pos": 158,
    "z": 4,
    "y": 860
  },
  {
    "pos": 159,
    "z": 42,
    "y": 972
  },
  {
    "pos": 160,
    "z": 36,
    "y": 1012
  },
  {
    "pos": 161,
    "z": 6,
    "y": 1069
  },
  {
    "pos": 162,
    "z": 52,
    "y": 1112
  },
  {
    "pos": 163,
    "z": 58,
    "y": 1141
  },
  {
    "pos": 171,
    "z": 168,
    "y": 862
  },
  {
    "pos": 173,
    "z": 132,
    "y": 751
  },
  {
    "pos": 176,
    "z": 142,
    "y": 597
  },
  {
    "pos": 180,
    "z": 125,
    "y": 432
  },
  {
    "pos": 181,
    "z": 130,
    "y": 431
  },
  {
    "pos": 182,
    "z": 136,
    "y": 470
  },
  {
    "pos": 183,
    "z": 179,
    "y": 568
  },
  {
    "pos": 184,
    "z": 137,
    "y": 542
  },
  {
    "pos": 185,
    "z": 112,
    "y": 607
  },
  {
    "pos": 186,
    "z": 80,
    "y": 717
  },
  {
    "pos": 187,
    "z": 112,
    "y": 804
  },
  {
    "pos": 188,
    "z": 91,
    "y": 888
  },
  {
    "pos": 189,
    "z": 136,
    "y": 983
  },
  {
    "pos": 190,
    "z": 38,
    "y": 1024
  },
  {
    "pos": 191,
    "z": 135,
    "y": 1056
  },
  {
    "pos": 192,
    "z": 134,
    "y": 1053
  },
  {
    "pos": 193,
    "z": 152,
    "y": 1145
  },
  {
    "pos": 200,
    "z": 206,
    "y": 804
  },
  {
    "pos": 203,
    "z": 194,
    "y": 614
  },
  {
    "pos": 205,
    "z": 177,
    "y": 588
  },
  {
    "pos": 207,
    "z": 179,
    "y": 425
  },
  {
    "pos": 208,
    "z": 163,
    "y": 458
  },
  {
    "pos": 209,
    "z": 168,
    "y": 486
  },
  {
    "pos": 210,
    "z": 164,
    "y": 552
  },
  {
    "pos": 211,
    "z": 171,
    "y": 573
  },
  {
    "pos": 212,
    "z": 153,
    "y": 631
  },
  {
    "pos": 213,
    "z": 176,
    "y": 702
  },
  {
    "pos": 214,
    "z": 169,
    "y": 706
  },
  {
    "pos": 215,
    "z": 266,
    "y": 804
  },
  {
    "pos": 216,
    "z": 226,
    "y": 946
  },
  {
    "pos": 217,
    "z": 185,
    "y": 964
  },
  {
    "pos": 218,
    "z": 210,
    "y": 991
  },
  {
    "pos": 219,
    "z": 216,
    "y": 1070
  },
  {
    "pos": 220,
    "z": 215,
    "y": 1070
  },
  {
    "pos": 221,
    "z": 206,
    "y": 1048
  },
  {
    "pos": 222,
    "z": 224,
    "y": 962
  },
  {
    "pos": 223,
    "z": 199,
    "y": 932
  },
  {
    "pos": 224,
    "z": 205,
    "y": 879
  },
  {
    "pos": 225,
    "z": 200,
    "y": 879
  },
  {
    "pos": 226,
    "z": 175,
    "y": 758
  },
  {
    "pos": 227,
    "z": 197,
    "y": 704
  },
  {
    "pos": 228,
    "z": 218,
    "y": 654
  },
  {
    "pos": 229,
    "z": 200,
    "y": 605
  },
  {
    "pos": 230,
    "z": 196,
    "y": 605
  },
  {
    "pos": 232,
    "z": 249,
    "y": 486
  },
  {
    "pos": 233,
    "z": 217,
    "y": 535
  },
  {
    "pos": 234,
    "z": 233,
    "y": 478
  },
  {
    "pos": 235,
    "z": 218,
    "y": 527
  },
  {
    "pos": 236,
    "z": 243,
    "y": 566
  },
  {
    "pos": 237,
    "z": 243,
    "y": 640
  },
  {
    "pos": 238,
    "z": 249,
    "y": 704
  },
  {
    "pos": 239,
    "z": 271,
    "y": 774
  },
  {
    "pos": 240,
    "z": 282,
    "y": 826
  },
  {
    "pos": 241,
    "z": 273,
    "y": 825
  },
  {
    "pos": 242,
    "z": 255,
    "y": 929
  },
  {
    "pos": 243,
    "z": 244,
    "y": 1024
  },
  {
    "pos": 244,
    "z": 247,
    "y": 1022
  },
  {
    "pos": 245,
    "z": 265,
    "y": 1059
  },
  {
    "pos": 246,
    "z": 254,
    "y": 1006
  },
  {
    "pos": 252,
    "z": 212,
    "y": 673
  },
  {
    "pos": 253,
    "z": 220,
    "y": 608
  },
  {
    "pos": 257,
    "z": 165,
    "y": 466
  },
  {
    "pos": 259,
    "z": 240,
    "y": 654
  },
  {
    "pos": 260,
    "z": 269,
    "y": 664
  },
  {
    "pos": 261,
    "z": 250,
    "y": 667
  },
  {
    "pos": 262,
    "z": 319,
    "y": 841
  },
  {
    "pos": 263,
    "z": 300,
    "y": 833
  },
  {
    "pos": 264,
    "z": 302,
    "y": 965
  },
  {
    "pos": 265,
    "z": 307,
    "y": 1016
  },
  {
    "pos": 266,
    "z": 305,
    "y": 1015
  },
  {
    "pos": 270,
    "z": 353,
    "y": 835
  },
  {
    "pos": 271,
    "z": 277,
    "y": 761
  },
  {
    "pos": 273,
    "z": 283,
    "y": 676
  },
  {
    "pos": 274,
    "z": 219,
    "y": 611
  },
  {
    "pos": 276,
    "z": 308,
    "y": 537
  },
  {
    "pos": 279,
    "z": 276,
    "y": 556
  },
  {
    "pos": 280,
    "z": 313,
    "y": 729
  },
  {
    "pos": 281,
    "z": 341,
    "y": 778
  },
  {
    "pos": 282,
    "z": 356,
    "y": 860
  },
  {
    "pos": 283,
    "z": 281,
    "y": 947
  },
  {
    "pos": 284,
    "z": 341,
    "y": 999
  },
  {
    "pos": 285,
    "z": 345,
    "y": 1039
  },
  {
    "pos": 286,
    "z": 335,
    "y": 988
  },
  {
    "pos": 291,
    "z": 341,
    "y": 905
  },
  {
    "pos": 292,
    "z": 363,
    "y": 843
  },
  {
    "pos": 294,
    "z": 339,
    "y": 734
  },
  {
    "pos": 300,
    "z": 397,
    "y": 528
  },
  {
    "pos": 301,
    "z": 331,
    "y": 590
  },
  {
    "pos": 302,
    "z": 322,
    "y": 685
  },
  {
    "pos": 303,
    "z": 396,
    "y": 661
  },
  {
    "pos": 304,
    "z": 377,
    "y": 733
  },
  {
    "pos": 305,
    "z": 388,
    "y": 835
  },
  {
    "pos": 306,
    "z": 375,
    "y": 894
  },
  {
    "pos": 307,
    "z": 487,
    "y": 966
  },
  {
    "pos": 308,
    "z": 477,
    "y": 969
  },
  {
    "pos": 309,
    "z": 406,
    "y": 1019
  },
  {
    "pos": 310,
    "z": 417,
    "y": 1023
  },
  {
    "pos": 311,
    "z": 462,
    "y": 1041
  },
  {
    "pos": 312,
    "z": 460,
    "y": 1039
  },
  {
    "pos": 314,
    "z": 419,
    "y": 889
  },
  {
    "pos": 319,
    "z": 428,
    "y": 602
  },
  {
    "pos": 321,
    "z": 446,
    "y": 523
  },
  {
    "pos": 323,
    "z": 426,
    "y": 526
  },
  {
    "pos": 324,
    "z": 422,
    "y": 551
  },
  {
    "pos": 325,
    "z": 433,
    "y": 592
  },
  {
    "pos": 326,
    "z": 417,
    "y": 620
  },
  {
    "pos": 327,
    "z": 465,
    "y": 729
  },
  {
    "pos": 328,
    "z": 475,
    "y": 789
  },
  {
    "pos": 329,
    "z": 447,
    "y": 861
  },
  {
    "pos": 330,
    "z": 546,
    "y": 944
  },
  {
    "pos": 331,
    "z": 463,
    "y": 938
  },
  {
    "pos": 332,
    "z": 442,
    "y": 1002
  },
  {
    "pos": 333,
    "z": 449,
    "y": 1006
  },
  {
    "pos": 338,
    "z": 473,
    "y": 812
  },
  {
    "pos": 341,
    "z": 520,
    "y": 688
  },
  {
    "pos": 342,
    "z": 429,
    "y": 602
  },
  {
    "pos": 345,
    "z": 481,
    "y": 477
  },
  {
    "pos": 347,
    "z": 526,
    "y": 556
  },
  {
    "pos": 348,
    "z": 496,
    "y": 643
  },
  {
    "pos": 349,
    "z": 581,
    "y": 698
  },
  {
    "pos": 350,
    "z": 569,
    "y": 919
  },
  {
    "pos": 351,
    "z": 571,
    "y": 923
  },
  {
    "pos": 352,
    "z": 559,
    "y": 984
  },
  {
    "pos": 353,
    "z": 551,
    "y": 990
  },
  {
    "pos": 354,
    "z": 539,
    "y": 959
  },
  {
    "pos": 358,
    "z": 465,
    "y": 844
  },
  {
    "pos": 359,
    "z": 473,
    "y": 805
  },
  {
    "pos": 362,
    "z": 470,
    "y": 703
  },
  {
    "pos": 363,
    "z": 549,
    "y": 564
  },
  {
    "pos": 365,
    "z": 607,
    "y": 692
  },
  {
    "pos": 366,
    "z": 605,
    "y": 554
  },
  {
    "pos": 367,
    "z": 574,
    "y": 645
  },
  {
    "pos": 369,
    "z": 651,
    "y": 747
  },
  {
    "pos": 370,
    "z": 671,
    "y": 823
  },
  {
    "pos": 371,
    "z": 584,
    "y": 882
  },
  {
    "pos": 372,
    "z": 645,
    "y": 938
  },
  {
    "pos": 373,
    "z": 642,
    "y": 1009
  },
  {
    "pos": 374,
    "z": 622,
    "y": 1015
  },
  {
    "pos": 380,
    "z": 556,
    "y": 747
  },
  {
    "pos": 385,
    "z": 569,
    "y": 578
  },
  {
    "pos": 386,
    "z": 600,
    "y": 610
  },
  {
    "pos": 387,
    "z": 609,
    "y": 686
  },
  {
    "pos": 388,
    "z": 685,
    "y": 733
  },
  {
    "pos": 389,
    "z": 681,
    "y": 842
  },
  {
    "pos": 390,
    "z": 669,
    "y": 877
  },
  {
    "pos": 391,
    "z": 633,
    "y": 927
  },
  {
    "pos": 392,
    "z": 663,
    "y": 1005
  },
  {
    "pos": 393,
    "z": 535,
    "y": 1045
  },
  {
    "pos": 396,
    "z": 637,
    "y": 915
  },
  {
    "pos": 398,
    "z": 603,
    "y": 797
  },
  {
    "pos": 399,
    "z": 590,
    "y": 746
  },
  {
    "pos": 403,
    "z": 642,
    "y": 576
  },
  {
    "pos": 404,
    "z": 673,
    "y": 609
  },
  {
    "pos": 405,
    "z": 720,
    "y": 672
  },
  {
    "pos": 406,
    "z": 702,
    "y": 738
  },
  {
    "pos": 407,
    "z": 735,
    "y": 822
  },
  {
    "pos": 408,
    "z": 708,
    "y": 887
  },
  {
    "pos": 409,
    "z": 669,
    "y": 892
  },
  {
    "pos": 410,
    "z": 666,
    "y": 923
  },
  {
    "pos": 411,
    "z": 662,
    "y": 923
  },
  {
    "pos": 413,
    "z": 616,
    "y": 910
  },
  {
    "pos": 420,
    "z": 676,
    "y": 638
  },
  {
    "pos": 421,
    "z": 752,
    "y": 676
  },
  {
    "pos": 422,
    "z": 725,
    "y": 755
  },
  {
    "pos": 423,
    "z": 736,
    "y": 848
  },
  {
    "pos": 424,
    "z": 648,
    "y": 925
  },
  {
    "pos": 431,
    "z": 588,
    "y": 682
  },
  {
    "pos": 434,
    "z": 775,
    "y": 645
  },
  {
    "pos": 435,
    "z": 797,
    "y": 749
  },
  {
    "pos": 436,
    "z": 813,
    "y": 758
  },
  {
    "pos": 437,
    "z": 809,
    "y": 823
  },
  {
    "pos": 438,
    "z": 843,
    "y": 920
  },
  {
    "pos": 439,
    "z": 831,
    "y": 925
  },
  {
    "pos": 440,
    "z": 791,
    "y": 958
  },
  {
    "pos": 442,
    "z": 761,
    "y": 875
  },
  {
    "pos": 445,
    "z": 770,
    "y": 751
  },
  {
    "pos": 447,
    "z": 779,
    "y": 591
  },
  {
    "pos": 448,
    "z": 792,
    "y": 600
  },
  {
    "pos": 449,
    "z": 861,
    "y": 593
  },
  {
    "pos": 450,
    "z": 886,
    "y": 677
  },
  {
    "pos": 451,
    "z": 870,
    "y": 689
  },
  {
    "pos": 452,
    "z": 839,
    "y": 848
  },
  {
    "pos": 453,
    "z": 853,
    "y": 889
  },
  {
    "pos": 454,
    "z": 843,
    "y": 913
  },
  {
    "pos": 457,
    "z": 845,
    "y": 808
  },
  {
    "pos": 459,
    "z": 842,
    "y": 719
  },
  {
    "pos": 460,
    "z": 862,
    "y": 639
  },
  {
    "pos": 461,
    "z": 847,
    "y": 665
  },
  {
    "pos": 462,
    "z": 941,
    "y": 652
  },
  {
    "pos": 463,
    "z": 934,
    "y": 740
  },
  {
    "pos": 464,
    "z": 1051,
    "y": 790
  },
  {
    "pos": 465,
    "z": 988,
    "y": 839
  },
  {
    "pos": 466,
    "z": 1007,
    "y": 879
  },
  {
    "pos": 467,
    "z": 926,
    "y": 883
  },
  {
    "pos": 468,
    "z": 930,
    "y": 884
  },
  {
    "pos": 469,
    "z": 899,
    "y": 790
  },
  {
    "pos": 472,
    "z": 912,
    "y": 611
  },
  {
    "pos": 473,
    "z": 976,
    "y": 630
  },
  {
    "pos": 474,
    "z": 1010,
    "y": 613
  },
  {
    "pos": 475,
    "z": 1007,
    "y": 682
  },
  {
    "pos": 476,
    "z": 1090,
    "y": 749
  },
  {
    "pos": 477,
    "z": 1067,
    "y": 734
  },
  {
    "pos": 479,
    "z": 1054,
    "y": 896
  },
  {
    "pos": 481,
    "z": 1006,
    "y": 742
  },
  {
    "pos": 482,
    "z": 1003,
    "y": 743
  },
  {
    "pos": 484,
    "z": 1016,
    "y": 669
  },
  {
    "pos": 485,
    "z": 1063,
    "y": 627
  },
  {
    "pos": 486,
    "z": 1088,
    "y": 636
  },
  {
    "pos": 487,
    "z": 1134,
    "y": 670
  },
  {
    "pos": 488,
    "z": 1160,
    "y": 743
  },
  {
    "pos": 489,
    "z": 1107,
    "y": 839
  },
  {
    "pos": 490,
    "z": 1082,
    "y": 823
  },
  {
    "pos": 491,
    "z": 1075,
    "y": 830
  },
  {
    "pos": 493,
    "z": 1070,
    "y": 714
  },
  {
    "pos": 494,
    "z": 1130,
    "y": 648
  },
  {
    "pos": 495,
    "z": 1210,
    "y": 674
  },
  {
    "pos": 496,
    "z": 1234,
    "y": 690
  },
  {
    "pos": 497,
    "z": 1157,
    "y": 714
  },
  {
    "pos": 498,
    "z": 1158,
    "y": 817
  },
  {
    "pos": 499,
    "z": 1150,
    "y": 876
  },
  {
    "pos": 0,
    "z": -378,
    "x": 336
  },
  {
    "pos": 1,
    "z": -307,
    "x": 335
  },
  {
    "pos": 2,
    "z": -276,
    "x": 327
  },
  {
    "pos": 3,
    "z": -270,
    "x": 283
  },
  {
    "pos": 4,
    "z": -191,
    "x": 326
  },
  {
    "pos": 5,
    "z": -200,
    "x": 328
  },
  {
    "pos": 6,
    "z": -153,
    "x": 258
  },
  {
    "pos": 7,
    "z": -153,
    "x": 257
  },
  {
    "pos": 8,
    "z": -425,
    "x": 373
  },
  {
    "pos": 15,
    "z": -243,
    "x": 672
  },
  {
    "pos": 17,
    "z": -356,
    "x": 824
  },
  {
    "pos": 19,
    "z": -357,
    "x": 1005
  },
  {
    "pos": 20,
    "z": -356,
    "x": 1003
  },
  {
    "pos": 21,
    "z": -322,
    "x": 971
  },
  {
    "pos": 23,
    "z": -381,
    "x": 1072
  },
  {
    "pos": 29,
    "z": -329,
    "x": 1149
  },
  {
    "pos": 30,
    "z": -335,
    "x": 1158
  },
  {
    "pos": 31,
    "z": -355,
    "x": 1110
  },
  {
    "pos": 32,
    "z": -364,
    "x": 1025
  },
  {
    "pos": 34,
    "z": -259,
    "x": 940
  },
  {
    "pos": 35,
    "z": -354,
    "x": 813
  },
  {
    "pos": 36,
    "z": -358,
    "x": 722
  },
  {
    "pos": 37,
    "z": -385,
    "x": 628
  },
  {
    "pos": 38,
    "z": -390,
    "x": 514
  },
  {
    "pos": 39,
    "z": -334,
    "x": 461
  },
  {
    "pos": 40,
    "z": -315,
    "x": 376
  },
  {
    "pos": 41,
    "z": -255,
    "x": 330
  },
  {
    "pos": 42,
    "z": -208,
    "x": 327
  },
  {
    "pos": 43,
    "z": -171,
    "x": 296
  },
  {
    "pos": 44,
    "z": -121,
    "x": 249
  },
  {
    "pos": 45,
    "z": -163,
    "x": 273
  },
  {
    "pos": 46,
    "z": -430,
    "x": 243
  },
  {
    "pos": 52,
    "z": -77,
    "x": 717
  },
  {
    "pos": 59,
    "z": -450,
    "x": 1104
  },
  {
    "pos": 61,
    "z": -159,
    "x": 1152
  },
  {
    "pos": 63,
    "z": -281,
    "x": 1182
  },
  {
    "pos": 65,
    "z": -217,
    "x": 1138
  },
  {
    "pos": 66,
    "z": -249,
    "x": 1128
  },
  {
    "pos": 68,
    "z": -270,
    "x": 883
  },
  {
    "pos": 69,
    "z": -288,
    "x": 793
  },
  {
    "pos": 70,
    "z": -171,
    "x": 718
  },
  {
    "pos": 71,
    "z": -108,
    "x": 661
  },
  {
    "pos": 72,
    "z": -169,
    "x": 542
  },
  {
    "pos": 73,
    "z": -233,
    "x": 498
  },
  {
    "pos": 74,
    "z": -165,
    "x": 415
  },
  {
    "pos": 75,
    "z": -113,
    "x": 334
  },
  {
    "pos": 76,
    "z": -112,
    "x": 322
  },
  {
    "pos": 77,
    "z": -132,
    "x": 367
  },
  {
    "pos": 87,
    "z": -4,
    "x": 780
  },
  {
    "pos": 90,
    "z": -49,
    "x": 945
  },
  {
    "pos": 96,
    "z": -131,
    "x": 1111
  },
  {
    "pos": 97,
    "z": -168,
    "x": 1055
  },
  {
    "pos": 98,
    "z": -167,
    "x": 1107
  },
  {
    "pos": 99,
    "z": -163,
    "x": 1038
  },
  {
    "pos": 100,
    "z": -132,
    "x": 909
  },
  {
    "pos": 101,
    "z": -179,
    "x": 815
  },
  {
    "pos": 102,
    "z": -166,
    "x": 714
  },
  {
    "pos": 103,
    "z": -199,
    "x": 581
  },
  {
    "pos": 104,
    "z": -109,
    "x": 517
  },
  {
    "pos": 105,
    "z": -158,
    "x": 477
  },
  {
    "pos": 106,
    "z": -112,
    "x": 452
  },
  {
    "pos": 107,
    "z": -60,
    "x": 360
  },
  {
    "pos": 108,
    "z": -76,
    "x": 403
  },
  {
    "pos": 111,
    "z": -44,
    "x": 368
  },
  {
    "pos": 115,
    "z": 50,
    "x": 563
  },
  {
    "pos": 125,
    "z": -1,
    "x": 1069
  },
  {
    "pos": 127,
    "z": -20,
    "x": 1117
  },
  {
    "pos": 128,
    "z": -9,
    "x": 1073
  },
  {
    "pos": 129,
    "z": -42,
    "x": 1088
  },
  {
    "pos": 130,
    "z": -64,
    "x": 1075
  },
  {
    "pos": 131,
    "z": -68,
    "x": 1016
  },
  {
    "pos": 132,
    "z": -91,
    "x": 927
  },
  {
    "pos": 133,
    "z": -60,
    "x": 830
  },
  {
    "pos": 134,
    "z": -27,
    "x": 734
  },
  {
    "pos": 135,
    "z": -32,
    "x": 653
  },
  {
    "pos": 136,
    "z": -1,
    "x": 599
  },
  {
    "pos": 137,
    "z": -22,
    "x": 485
  },
  {
    "pos": 138,
    "z": -29,
    "x": 507
  },
  {
    "pos": 139,
    "z": 58,
    "x": 435
  },
  {
    "pos": 140,
    "z": 54,
    "x": 439
  },
  {
    "pos": 141,
    "z": 30,
    "x": 314
  },
  {
    "pos": 146,
    "z": 96,
    "x": 534
  },
  {
    "pos": 157,
    "z": 37,
    "x": 1053
  },
  {
    "pos": 158,
    "z": 41,
    "x": 1074
  },
  {
    "pos": 159,
    "z": 56,
    "x": 1094
  },
  {
    "pos": 160,
    "z": 33,
    "x": 1043
  },
  {
    "pos": 161,
    "z": -3,
    "x": 1005
  },
  {
    "pos": 162,
    "z": 15,
    "x": 936
  },
  {
    "pos": 163,
    "z": 7,
    "x": 862
  },
  {
    "pos": 164,
    "z": 104,
    "x": 781
  },
  {
    "pos": 166,
    "z": 23,
    "x": 594
  },
  {
    "pos": 167,
    "z": 65,
    "x": 460
  },
  {
    "pos": 168,
    "z": 41,
    "x": 481
  },
  {
    "pos": 169,
    "z": 61,
    "x": 424
  },
  {
    "pos": 170,
    "z": 60,
    "x": 424
  },
  {
    "pos": 172,
    "z": 105,
    "x": 393
  },
  {
    "pos": 173,
    "z": 96,
    "x": 391
  },
  {
    "pos": 183,
    "z": 199,
    "x": 905
  },
  {
    "pos": 184,
    "z": 180,
    "x": 926
  },
  {
    "pos": 188,
    "z": 96,
    "x": 1113
  },
  {
    "pos": 189,
    "z": 126,
    "x": 1086
  },
  {
    "pos": 190,
    "z": 93,
    "x": 950
  },
  {
    "pos": 191,
    "z": 103,
    "x": 896
  },
  {
    "pos": 192,
    "z": 119,
    "x": 861
  },
  {
    "pos": 193,
    "z": 136,
    "x": 802
  },
  {
    "pos": 194,
    "z": 118,
    "x": 736
  },
  {
    "pos": 195,
    "z": 129,
    "x": 653
  },
  {
    "pos": 196,
    "z": 135,
    "x": 581
  },
  {
    "pos": 197,
    "z": 151,
    "x": 513
  },
  {
    "pos": 198,
    "z": 114,
    "x": 438
  },
  {
    "pos": 199,
    "z": 118,
    "x": 409
  },
  {
    "pos": 200,
    "z": 279,
    "x": 452
  },
  {
    "pos": 205,
    "z": 193,
    "x": 659
  },
  {
    "pos": 206,
    "z": 185,
    "x": 671
  },
  {
    "pos": 209,
    "z": 187,
    "x": 862
  },
  {
    "pos": 210,
    "z": 198,
    "x": 877
  },
  {
    "pos": 211,
    "z": 193,
    "x": 918
  },
  {
    "pos": 213,
    "z": 191,
    "x": 963
  },
  {
    "pos": 214,
    "z": 157,
    "x": 920
  },
  {
    "pos": 215,
    "z": 225,
    "x": 1028
  },
  {
    "pos": 216,
    "z": 220,
    "x": 1026
  },
  {
    "pos": 217,
    "z": 161,
    "x": 920
  },
  {
    "pos": 219,
    "z": 254,
    "x": 791
  },
  {
    "pos": 220,
    "z": 154,
    "x": 735
  },
  {
    "pos": 221,
    "z": 197,
    "x": 633
  },
  {
    "pos": 222,
    "z": 210,
    "x": 618
  },
  {
    "pos": 225,
    "z": 216,
    "x": 464
  },
  {
    "pos": 226,
    "z": 214,
    "x": 469
  },
  {
    "pos": 228,
    "z": 215,
    "x": 533
  },
  {
    "pos": 229,
    "z": 199,
    "x": 616
  },
  {
    "pos": 230,
    "z": 218,
    "x": 651
  },
  {
    "pos": 231,
    "z": 238,
    "x": 706
  },
  {
    "pos": 232,
    "z": 232,
    "x": 706
  },
  {
    "pos": 233,
    "z": 204,
    "x": 875
  },
  {
    "pos": 235,
    "z": 199,
    "x": 911
  },
  {
    "pos": 237,
    "z": 237,
    "x": 996
  },
  {
    "pos": 238,
    "z": 223,
    "x": 937
  },
  {
    "pos": 240,
    "z": 252,
    "x": 1050
  },
  {
    "pos": 241,
    "z": 270,
    "x": 1001
  },
  {
    "pos": 242,
    "z": 254,
    "x": 918
  },
  {
    "pos": 243,
    "z": 254,
    "x": 852
  },
  {
    "pos": 244,
    "z": 270,
    "x": 790
  },
  {
    "pos": 245,
    "z": 341,
    "x": 757
  },
  {
    "pos": 246,
    "z": 254,
    "x": 649
  },
  {
    "pos": 247,
    "z": 248,
    "x": 575
  },
  {
    "pos": 248,
    "z": 273,
    "x": 474
  },
  {
    "pos": 249,
    "z": 271,
    "x": 472
  },
  {
    "pos": 250,
    "z": 260,
    "x": 459
  },
  {
    "pos": 252,
    "z": 242,
    "x": 560
  },
  {
    "pos": 253,
    "z": 237,
    "x": 588
  },
  {
    "pos": 254,
    "z": 330,
    "x": 637
  },
  {
    "pos": 257,
    "z": 244,
    "x": 833
  },
  {
    "pos": 261,
    "z": 236,
    "x": 946
  },
  {
    "pos": 262,
    "z": 289,
    "x": 944
  },
  {
    "pos": 263,
    "z": 156,
    "x": 920
  },
  {
    "pos": 264,
    "z": 232,
    "x": 842
  },
  {
    "pos": 265,
    "z": 313,
    "x": 825
  },
  {
    "pos": 266,
    "z": 339,
    "x": 694
  },
  {
    "pos": 267,
    "z": 303,
    "x": 632
  },
  {
    "pos": 268,
    "z": 326,
    "x": 543
  },
  {
    "pos": 270,
    "z": 323,
    "x": 473
  },
  {
    "pos": 274,
    "z": 289,
    "x": 639
  },
  {
    "pos": 275,
    "z": 371,
    "x": 697
  },
  {
    "pos": 278,
    "z": 324,
    "x": 790
  },
  {
    "pos": 280,
    "z": 314,
    "x": 940
  },
  {
    "pos": 282,
    "z": 328,
    "x": 1030
  },
  {
    "pos": 283,
    "z": 330,
    "x": 974
  },
  {
    "pos": 284,
    "z": 349,
    "x": 950
  },
  {
    "pos": 285,
    "z": 356,
    "x": 889
  },
  {
    "pos": 286,
    "z": 373,
    "x": 808
  },
  {
    "pos": 287,
    "z": 355,
    "x": 733
  },
  {
    "pos": 288,
    "z": 399,
    "x": 675
  },
  {
    "pos": 289,
    "z": 386,
    "x": 587
  },
  {
    "pos": 290,
    "z": 383,
    "x": 581
  },
  {
    "pos": 291,
    "z": 387,
    "x": 455
  },
  {
    "pos": 292,
    "z": 370,
    "x": 453
  },
  {
    "pos": 293,
    "z": 369,
    "x": 451
  },
  {
    "pos": 295,
    "z": 335,
    "x": 651
  },
  {
    "pos": 297,
    "z": 341,
    "x": 638
  },
  {
    "pos": 298,
    "z": 361,
    "x": 709
  },
  {
    "pos": 300,
    "z": 348,
    "x": 905
  },
  {
    "pos": 304,
    "z": 364,
    "x": 983
  },
  {
    "pos": 305,
    "z": 357,
    "x": 1020
  },
  {
    "pos": 306,
    "z": 373,
    "x": 973
  },
  {
    "pos": 307,
    "z": 452,
    "x": 1014
  },
  {
    "pos": 308,
    "z": 412,
    "x": 951
  },
  {
    "pos": 309,
    "z": 430,
    "x": 836
  },
  {
    "pos": 310,
    "z": 443,
    "x": 729
  },
  {
    "pos": 311,
    "z": 529,
    "x": 671
  },
  {
    "pos": 312,
    "z": 456,
    "x": 619
  },
  {
    "pos": 313,
    "z": 429,
    "x": 575
  },
  {
    "pos": 314,
    "z": 428,
    "x": 542
  },
  {
    "pos": 315,
    "z": 445,
    "x": 482
  },
  {
    "pos": 316,
    "z": 445,
    "x": 488
  },
  {
    "pos": 320,
    "z": 433,
    "x": 700
  },
  {
    "pos": 321,
    "z": 428,
    "x": 786
  },
  {
    "pos": 322,
    "z": 430,
    "x": 787
  },
  {
    "pos": 328,
    "z": 440,
    "x": 1040
  },
  {
    "pos": 329,
    "z": 438,
    "x": 953
  },
  {
    "pos": 330,
    "z": 569,
    "x": 973
  },
  {
    "pos": 331,
    "z": 475,
    "x": 882
  },
  {
    "pos": 332,
    "z": 478,
    "x": 816
  },
  {
    "pos": 333,
    "z": 493,
    "x": 735
  },
  {
    "pos": 334,
    "z": 560,
    "x": 656
  },
  {
    "pos": 335,
    "z": 511,
    "x": 607
  },
  {
    "pos": 336,
    "z": 532,
    "x": 525
  },
  {
    "pos": 337,
    "z": 514,
    "x": 488
  },
  {
    "pos": 338,
    "z": 466,
    "x": 533
  },
  {
    "pos": 342,
    "z": 456,
    "x": 650
  },
  {
    "pos": 343,
    "z": 468,
    "x": 709
  },
  {
    "pos": 344,
    "z": 465,
    "x": 707
  },
  {
    "pos": 345,
    "z": 476,
    "x": 802
  },
  {
    "pos": 346,
    "z": 528,
    "x": 811
  },
  {
    "pos": 350,
    "z": 592,
    "x": 938
  },
  {
    "pos": 351,
    "z": 553,
    "x": 902
  },
  {
    "pos": 352,
    "z": 580,
    "x": 834
  },
  {
    "pos": 354,
    "z": 556,
    "x": 693
  },
  {
    "pos": 355,
    "z": 676,
    "x": 640
  },
  {
    "pos": 356,
    "z": 647,
    "x": 618
  },
  {
    "pos": 357,
    "z": 666,
    "x": 496
  },
  {
    "pos": 362,
    "z": 492,
    "x": 626
  },
  {
    "pos": 364,
    "z": 485,
    "x": 782
  },
  {
    "pos": 365,
    "z": 541,
    "x": 823
  },
  {
    "pos": 366,
    "z": 529,
    "x": 813
  },
  {
    "pos": 367,
    "z": 552,
    "x": 893
  },
  {
    "pos": 368,
    "z": 549,
    "x": 892
  },
  {
    "pos": 369,
    "z": 567,
    "x": 1020
  },
  {
    "pos": 370,
    "z": 640,
    "x": 1005
  },
  {
    "pos": 371,
    "z": 579,
    "x": 921
  },
  {
    "pos": 372,
    "z": 625,
    "x": 924
  },
  {
    "pos": 373,
    "z": 651,
    "x": 868
  },
  {
    "pos": 374,
    "z": 628,
    "x": 768
  },
  {
    "pos": 375,
    "z": 633,
    "x": 689
  },
  {
    "pos": 376,
    "z": 698,
    "x": 588
  },
  {
    "pos": 377,
    "z": 572,
    "x": 581
  },
  {
    "pos": 381,
    "z": 544,
    "x": 589
  },
  {
    "pos": 385,
    "z": 541,
    "x": 825
  },
  {
    "pos": 386,
    "z": 560,
    "x": 889
  },
  {
    "pos": 387,
    "z": 561,
    "x": 882
  },
  {
    "pos": 388,
    "z": 612,
    "x": 944
  },
  {
    "pos": 389,
    "z": 657,
    "x": 951
  },
  {
    "pos": 390,
    "z": 651,
    "x": 903
  },
  {
    "pos": 391,
    "z": 618,
    "x": 855
  },
  {
    "pos": 392,
    "z": 727,
    "x": 834
  },
  {
    "pos": 393,
    "z": 691,
    "x": 715
  },
  {
    "pos": 394,
    "z": 695,
    "x": 642
  },
  {
    "pos": 395,
    "z": 704,
    "x": 592
  },
  {
    "pos": 396,
    "z": 681,
    "x": 580
  },
  {
    "pos": 397,
    "z": 664,
    "x": 484
  },
  {
    "pos": 402,
    "z": 604,
    "x": 777
  },
  {
    "pos": 405,
    "z": 642,
    "x": 951
  },
  {
    "pos": 406,
    "z": 664,
    "x": 963
  },
  {
    "pos": 407,
    "z": 684,
    "x": 964
  },
  {
    "pos": 408,
    "z": 619,
    "x": 933
  },
  {
    "pos": 409,
    "z": 675,
    "x": 822
  },
  {
    "pos": 410,
    "z": 689,
    "x": 760
  },
  {
    "pos": 411,
    "z": 708,
    "x": 667
  },
  {
    "pos": 412,
    "z": 771,
    "x": 608
  },
  {
    "pos": 413,
    "z": 726,
    "x": 535
  },
  {
    "pos": 414,
    "z": 720,
    "x": 546
  },
  {
    "pos": 417,
    "z": 628,
    "x": 668
  },
  {
    "pos": 423,
    "z": 714,
    "x": 884
  },
  {
    "pos": 424,
    "z": 724,
    "x": 829
  },
  {
    "pos": 425,
    "z": 672,
    "x": 751
  },
  {
    "pos": 426,
    "z": 767,
    "x": 690
  },
  {
    "pos": 427,
    "z": 726,
    "x": 581
  },
  {
    "pos": 428,
    "z": 753,
    "x": 584
  },
  {
    "pos": 429,
    "z": 747,
    "x": 580
  },
  {
    "pos": 431,
    "z": 632,
    "x": 703
  },
  {
    "pos": 434,
    "z": 708,
    "x": 821
  },
  {
    "pos": 436,
    "z": 736,
    "x": 912
  },
  {
    "pos": 437,
    "z": 785,
    "x": 870
  },
  {
    "pos": 438,
    "z": 870,
    "x": 875
  },
  {
    "pos": 439,
    "z": 821,
    "x": 816
  },
  {
    "pos": 440,
    "z": 849,
    "x": 723
  },
  {
    "pos": 441,
    "z": 842,
    "x": 692
  },
  {
    "pos": 442,
    "z": 839,
    "x": 689
  },
  {
    "pos": 443,
    "z": 813,
    "x": 584
  },
  {
    "pos": 444,
    "z": 872,
    "x": 549
  },
  {
    "pos": 445,
    "z": 774,
    "x": 673
  },
  {
    "pos": 450,
    "z": 786,
    "x": 921
  },
  {
    "pos": 451,
    "z": 825,
    "x": 913
  },
  {
    "pos": 452,
    "z": 862,
    "x": 821
  },
  {
    "pos": 453,
    "z": 935,
    "x": 728
  },
  {
    "pos": 454,
    "z": 933,
    "x": 715
  },
  {
    "pos": 455,
    "z": 1003,
    "x": 643
  },
  {
    "pos": 456,
    "z": 931,
    "x": 537
  },
  {
    "pos": 457,
    "z": 898,
    "x": 563
  },
  {
    "pos": 459,
    "z": 922,
    "x": 628
  },
  {
    "pos": 461,
    "z": 808,
    "x": 771
  },
  {
    "pos": 463,
    "z": 906,
    "x": 831
  },
  {
    "pos": 464,
    "z": 959,
    "x": 929
  },
  {
    "pos": 465,
    "z": 979,
    "x": 882
  },
  {
    "pos": 466,
    "z": 981,
    "x": 886
  },
  {
    "pos": 467,
    "z": 974,
    "x": 791
  },
  {
    "pos": 468,
    "z": 983,
    "x": 694
  },
  {
    "pos": 469,
    "z": 905,
    "x": 654
  },
  {
    "pos": 473,
    "z": 928,
    "x": 772
  },
  {
    "pos": 477,
    "z": 1016,
    "x": 868
  },
  {
    "pos": 478,
    "z": 1024,
    "x": 813
  },
  {
    "pos": 479,
    "z": 1202,
    "x": 722
  },
  {
    "pos": 480,
    "z": 1037,
    "x": 668
  },
  {
    "pos": 481,
    "z": 1038,
    "x": 656
  },
  {
    "pos": 482,
    "z": 1061,
    "x": 636
  },
  {
    "pos": 488,
    "z": 1066,
    "x": 869
  },
  {
    "pos": 489,
    "z": 1103,
    "x": 827
  },
  {
    "pos": 491,
    "z": 1123,
    "x": 692
  },
  {
    "pos": 492,
    "z": 1119,
    "x": 688
  },
  {
    "pos": 493,
    "z": 1005,
    "x": 699
  },
  {
    "pos": 498,
    "z": 1159,
    "x": 808
  },
  {
    "pos": 499,
    "z": 1230,
    "x": 722
  },
  {
    "pos": 0,
    "z": -385,
    "y": 1076
  },
  {
    "pos": 1,
    "z": -323,
    "y": 1274
  },
  {
    "pos": 2,
    "z": -361,
    "y": 1070
  },
  {
    "pos": 3,
    "z": -377,
    "y": 1000
  },
  {
    "pos": 4,
    "z": -327,
    "y": 910
  },
  {
    "pos": 5,
    "z": -356,
    "y": 845
  },
  {
    "pos": 6,
    "z": -333,
    "y": 743
  },
  {
    "pos": 7,
    "z": -355,
    "y": 682
  },
  {
    "pos": 8,
    "z": -344,
    "y": 580
  },
  {
    "pos": 9,
    "z": -319,
    "y": 502
  },
  {
    "pos": 10,
    "z": -188,
    "y": 413
  },
  {
    "pos": 11,
    "z": -270,
    "y": 396
  },
  {
    "pos": 12,
    "z": -263,
    "y": 378
  },
  {
    "pos": 14,
    "z": -218,
    "y": 297
  },
  {
    "pos": 15,
    "z": -195,
    "y": 290
  },
  {
    "pos": 16,
    "z": -201,
    "y": 285
  },
  {
    "pos": 17,
    "z": -387,
    "y": 437
  },
  {
    "pos": 20,
    "z": -333,
    "y": 511
  },
  {
    "pos": 21,
    "z": -380,
    "y": 497
  },
  {
    "pos": 23,
    "z": -335,
    "y": 549
  },
  {
    "pos": 25,
    "z": -116,
    "y": 702
  },
  {
    "pos": 26,
    "z": -401,
    "y": 726
  },
  {
    "pos": 27,
    "z": -138,
    "y": 798
  },
  {
    "pos": 28,
    "z": -323,
    "y": 918
  },
  {
    "pos": 29,
    "z": -386,
    "y": 971
  },
  {
    "pos": 32,
    "z": -448,
    "y": 1036
  },
  {
    "pos": 33,
    "z": -444,
    "y": 1044
  },
  {
    "pos": 38,
    "z": -255,
    "y": 1238
  },
  {
    "pos": 40,
    "z": -268,
    "y": 1201
  },
  {
    "pos": 41,
    "z": -270,
    "y": 1145
  },
  {
    "pos": 42,
    "z": -266,
    "y": 1039
  },
  {
    "pos": 43,
    "z": -256,
    "y": 979
  },
  {
    "pos": 44,
    "z": -217,
    "y": 923
  },
  {
    "pos": 45,
    "z": -232,
    "y": 921
  },
  {
    "pos": 46,
    "z": -286,
    "y": 720
  },
  {
    "pos": 47,
    "z": -279,
    "y": 623
  },
  {
    "pos": 48,
    "z": -248,
    "y": 538
  },
  {
    "pos": 49,
    "z": -212,
    "y": 467
  },
  {
    "pos": 50,
    "z": -227,
    "y": 458
  },
  {
    "pos": 52,
    "z": -443,
    "y": 462
  },
  {
    "pos": 53,
    "z": -430,
    "y": 477
  },
  {
    "pos": 57,
    "z": -50,
    "y": 487
  },
  {
    "pos": 60,
    "z": -91,
    "y": 686
  },
  {
    "pos": 62,
    "z": -88,
    "y": 801
  },
  {
    "pos": 63,
    "z": -99,
    "y": 861
  },
  {
    "pos": 72,
    "z": -116,
    "y": 1178
  },
  {
    "pos": 73,
    "z": -174,
    "y": 1119
  },
  {
    "pos": 74,
    "z": -177,
    "y": 1119
  },
  {
    "pos": 75,
    "z": -130,
    "y": 1083
  },
  {
    "pos": 76,
    "z": -162,
    "y": 964
  },
  {
    "pos": 77,
    "z": -168,
    "y": 967
  },
  {
    "pos": 78,
    "z": -169,
    "y": 773
  },
  {
    "pos": 79,
    "z": -196,
    "y": 668
  },
  {
    "pos": 80,
    "z": -196,
    "y": 587
  },
  {
    "pos": 81,
    "z": -186,
    "y": 522
  },
  {
    "pos": 82,
    "z": -155,
    "y": 447
  },
  {
    "pos": 83,
    "z": -140,
    "y": 403
  },
  {
    "pos": 84,
    "z": -125,
    "y": 346
  },
  {
    "pos": 85,
    "z": -136,
    "y": 308
  },
  {
    "pos": 86,
    "z": -444,
    "y": 461
  },
  {
    "pos": 87,
    "z": -443,
    "y": 461
  },
  {
    "pos": 90,
    "z": -34,
    "y": 488
  },
  {
    "pos": 92,
    "z": -37,
    "y": 564
  },
  {
    "pos": 96,
    "z": -32,
    "y": 843
  },
  {
    "pos": 98,
    "z": -28,
    "y": 947
  },
  {
    "pos": 103,
    "z": -170,
    "y": 1110
  },
  {
    "pos": 104,
    "z": -77,
    "y": 1214
  },
  {
    "pos": 105,
    "z": -133,
    "y": 1102
  },
  {
    "pos": 108,
    "z": -113,
    "y": 929
  },
  {
    "pos": 109,
    "z": -123,
    "y": 842
  },
  {
    "pos": 110,
    "z": -133,
    "y": 756
  },
  {
    "pos": 111,
    "z": -121,
    "y": 679
  },
  {
    "pos": 112,
    "z": -73,
    "y": 597
  },
  {
    "pos": 113,
    "z": -94,
    "y": 527
  },
  {
    "pos": 114,
    "z": -87,
    "y": 476
  },
  {
    "pos": 115,
    "z": -90,
    "y": 477
  },
  {
    "pos": 116,
    "z": -36,
    "y": 383
  },
  {
    "pos": 117,
    "z": -1,
    "y": 348
  },
  {
    "pos": 121,
    "z": -38,
    "y": 484
  },
  {
    "pos": 124,
    "z": 34,
    "y": 599
  },
  {
    "pos": 129,
    "z": 55,
    "y": 909
  },
  {
    "pos": 135,
    "z": 27,
    "y": 1166
  },
  {
    "pos": 139,
    "z": 51,
    "y": 994
  },
  {
    "pos": 140,
    "z": -6,
    "y": 1004
  },
  {
    "pos": 141,
    "z": -26,
    "y": 987
  },
  {
    "pos": 142,
    "z": -6,
    "y": 806
  },
  {
    "pos": 143,
    "z": 24,
    "y": 672
  },
  {
    "pos": 144,
    "z": -29,
    "y": 623
  },
  {
    "pos": 145,
    "z": 18,
    "y": 504
  },
  {
    "pos": 146,
    "z": 87,
    "y": 472
  },
  {
    "pos": 147,
    "z": 35,
    "y": 415
  },
  {
    "pos": 148,
    "z": 32,
    "y": 413
  },
  {
    "pos": 149,
    "z": 72,
    "y": 373
  },
  {
    "pos": 150,
    "z": 66,
    "y": 368
  },
  {
    "pos": 166,
    "z": 8,
    "y": 1149
  },
  {
    "pos": 167,
    "z": 60,
    "y": 1116
  },
  {
    "pos": 168,
    "z": 5,
    "y": 1062
  },
  {
    "pos": 169,
    "z": 42,
    "y": 972
  },
  {
    "pos": 170,
    "z": 39,
    "y": 905
  },
  {
    "pos": 171,
    "z": 86,
    "y": 851
  },
  {
    "pos": 172,
    "z": 53,
    "y": 738
  },
  {
    "pos": 173,
    "z": 50,
    "y": 661
  },
  {
    "pos": 174,
    "z": 61,
    "y": 577
  },
  {
    "pos": 175,
    "z": 96,
    "y": 510
  },
  {
    "pos": 177,
    "z": 126,
    "y": 410
  },
  {
    "pos": 178,
    "z": 117,
    "y": 408
  },
  {
    "pos": 180,
    "z": 147,
    "y": 411
  },
  {
    "pos": 185,
    "z": 172,
    "y": 664
  },
  {
    "pos": 190,
    "z": 93,
    "y": 922
  },
  {
    "pos": 191,
    "z": 95,
    "y": 972
  },
  {
    "pos": 194,
    "z": 162,
    "y": 1084
  },
  {
    "pos": 195,
    "z": 150,
    "y": 1061
  },
  {
    "pos": 196,
    "z": 156,
    "y": 1067
  },
  {
    "pos": 197,
    "z": 152,
    "y": 1047
  },
  {
    "pos": 198,
    "z": 136,
    "y": 1012
  },
  {
    "pos": 199,
    "z": 139,
    "y": 963
  },
  {
    "pos": 200,
    "z": 267,
    "y": 749
  },
  {
    "pos": 201,
    "z": 119,
    "y": 682
  },
  {
    "pos": 202,
    "z": 95,
    "y": 640
  },
  {
    "pos": 203,
    "z": 149,
    "y": 545
  },
  {
    "pos": 206,
    "z": 166,
    "y": 418
  },
  {
    "pos": 207,
    "z": 182,
    "y": 364
  },
  {
    "pos": 208,
    "z": 172,
    "y": 444
  },
  {
    "pos": 209,
    "z": 172,
    "y": 501
  },
  {
    "pos": 210,
    "z": 164,
    "y": 535
  },
  {
    "pos": 211,
    "z": 175,
    "y": 613
  },
  {
    "pos": 212,
    "z": 177,
    "y": 656
  },
  {
    "pos": 213,
    "z": 195,
    "y": 694
  },
  {
    "pos": 214,
    "z": 204,
    "y": 827
  },
  {
    "pos": 215,
    "z": 241,
    "y": 824
  },
  {
    "pos": 218,
    "z": 248,
    "y": 940
  },
  {
    "pos": 219,
    "z": 228,
    "y": 954
  },
  {
    "pos": 220,
    "z": 178,
    "y": 990
  },
  {
    "pos": 221,
    "z": 161,
    "y": 1070
  },
  {
    "pos": 222,
    "z": 210,
    "y": 956
  },
  {
    "pos": 223,
    "z": 159,
    "y": 927
  },
  {
    "pos": 224,
    "z": 178,
    "y": 875
  },
  {
    "pos": 225,
    "z": 259,
    "y": 756
  },
  {
    "pos": 226,
    "z": 173,
    "y": 721
  },
  {
    "pos": 227,
    "z": 178,
    "y": 643
  },
  {
    "pos": 228,
    "z": 200,
    "y": 559
  },
  {
    "pos": 229,
    "z": 180,
    "y": 530
  },
  {
    "pos": 230,
    "z": 203,
    "y": 504
  },
  {
    "pos": 231,
    "z": 229,
    "y": 503
  },
  {
    "pos": 232,
    "z": 254,
    "y": 461
  },
  {
    "pos": 233,
    "z": 251,
    "y": 461
  },
  {
    "pos": 238,
    "z": 253,
    "y": 725
  },
  {
    "pos": 239,
    "z": 281,
    "y": 783
  },
  {
    "pos": 245,
    "z": 282,
    "y": 1078
  },
  {
    "pos": 246,
    "z": 257,
    "y": 996
  },
  {
    "pos": 247,
    "z": 221,
    "y": 981
  },
  {
    "pos": 248,
    "z": 290,
    "y": 966
  },
  {
    "pos": 249,
    "z": 246,
    "y": 885
  },
  {
    "pos": 250,
    "z": 260,
    "y": 702
  },
  {
    "pos": 251,
    "z": 285,
    "y": 586
  },
  {
    "pos": 252,
    "z": 173,
    "y": 643
  },
  {
    "pos": 254,
    "z": 301,
    "y": 494
  },
  {
    "pos": 255,
    "z": 294,
    "y": 493
  },
  {
    "pos": 266,
    "z": 318,
    "y": 1008
  },
  {
    "pos": 267,
    "z": 253,
    "y": 996
  },
  {
    "pos": 268,
    "z": 342,
    "y": 964
  },
  {
    "pos": 269,
    "z": 315,
    "y": 941
  },
  {
    "pos": 271,
    "z": 284,
    "y": 744
  },
  {
    "pos": 272,
    "z": 279,
    "y": 670
  },
  {
    "pos": 273,
    "z": 300,
    "y": 579
  },
  {
    "pos": 274,
    "z": 293,
    "y": 564
  },
  {
    "pos": 276,
    "z": 315,
    "y": 521
  },
  {
    "pos": 280,
    "z": 335,
    "y": 725
  },
  {
    "pos": 286,
    "z": 324,
    "y": 1028
  },
  {
    "pos": 287,
    "z": 319,
    "y": 1006
  },
  {
    "pos": 289,
    "z": 369,
    "y": 1073
  },
  {
    "pos": 290,
    "z": 369,
    "y": 950
  },
  {
    "pos": 291,
    "z": 397,
    "y": 906
  },
  {
    "pos": 292,
    "z": 416,
    "y": 844
  },
  {
    "pos": 293,
    "z": 341,
    "y": 674
  },
  {
    "pos": 294,
    "z": 369,
    "y": 674
  },
  {
    "pos": 295,
    "z": 368,
    "y": 597
  },
  {
    "pos": 296,
    "z": 373,
    "y": 540
  },
  {
    "pos": 297,
    "z": 277,
    "y": 512
  },
  {
    "pos": 298,
    "z": 316,
    "y": 527
  },
  {
    "pos": 299,
    "z": 358,
    "y": 483
  },
  {
    "pos": 311,
    "z": 507,
    "y": 1087
  },
  {
    "pos": 312,
    "z": 443,
    "y": 979
  },
  {
    "pos": 313,
    "z": 446,
    "y": 944
  },
  {
    "pos": 314,
    "z": 432,
    "y": 940
  },
  {
    "pos": 315,
    "z": 486,
    "y": 821
  },
  {
    "pos": 316,
    "z": 473,
    "y": 693
  },
  {
    "pos": 317,
    "z": 468,
    "y": 655
  },
  {
    "pos": 318,
    "z": 486,
    "y": 559
  },
  {
    "pos": 320,
    "z": 470,
    "y": 483
  },
  {
    "pos": 321,
    "z": 474,
    "y": 484
  },
  {
    "pos": 322,
    "z": 398,
    "y": 425
  },
  {
    "pos": 325,
    "z": 425,
    "y": 623
  },
  {
    "pos": 326,
    "z": 427,
    "y": 622
  },
  {
    "pos": 334,
    "z": 519,
    "y": 1021
  },
  {
    "pos": 336,
    "z": 538,
    "y": 971
  },
  {
    "pos": 337,
    "z": 557,
    "y": 896
  },
  {
    "pos": 338,
    "z": 540,
    "y": 786
  },
  {
    "pos": 339,
    "z": 535,
    "y": 729
  },
  {
    "pos": 340,
    "z": 579,
    "y": 634
  },
  {
    "pos": 341,
    "z": 552,
    "y": 637
  },
  {
    "pos": 342,
    "z": 452,
    "y": 551
  },
  {
    "pos": 343,
    "z": 507,
    "y": 535
  },
  {
    "pos": 344,
    "z": -308,
    "y": 1
  },
  {
    "pos": 345,
    "z": -306,
    "y": 2
  },
  {
    "pos": 346,
    "z": -307,
    "y": 2
  },
  {
    "pos": 347,
    "z": -306,
    "y": 2
  },
  {
    "pos": 348,
    "z": -305,
    "y": 3
  },
  {
    "pos": 349,
    "z": -305,
    "y": 2
  },
  {
    "pos": 350,
    "z": -308,
    "y": 1
  },
  {
    "pos": 351,
    "z": 479,
    "y": 908
  },
  {
    "pos": 352,
    "z": -305,
    "y": 1
  },
  {
    "pos": 353,
    "z": -304,
    "y": 1
  },
  {
    "pos": 354,
    "z": -305,
    "y": 4
  },
  {
    "pos": 355,
    "z": 618,
    "y": 1019
  },
  {
    "pos": 356,
    "z": 594,
    "y": 1010
  },
  {
    "pos": 357,
    "z": 639,
    "y": 896
  },
  {
    "pos": 358,
    "z": 582,
    "y": 851
  },
  {
    "pos": 359,
    "z": 561,
    "y": 851
  },
  {
    "pos": 360,
    "z": 657,
    "y": 678
  },
  {
    "pos": 361,
    "z": 548,
    "y": 649
  },
  {
    "pos": 362,
    "z": -303,
    "y": 3
  },
  {
    "pos": 363,
    "z": -303,
    "y": 3
  },
  {
    "pos": 364,
    "z": -303,
    "y": 0
  },
  {
    "pos": 365,
    "z": -303,
    "y": 1
  },
  {
    "pos": 366,
    "z": -303,
    "y": 7
  },
  {
    "pos": 367,
    "z": -302,
    "y": 1
  },
  {
    "pos": 368,
    "z": 515,
    "y": 709
  },
  {
    "pos": 369,
    "z": -303,
    "y": 9
  },
  {
    "pos": 370,
    "z": -302,
    "y": 2
  },
  {
    "pos": 371,
    "z": -302,
    "y": 2
  },
  {
    "pos": 372,
    "z": -302,
    "y": 4
  },
  {
    "pos": 373,
    "z": -301,
    "y": 2
  },
  {
    "pos": 374,
    "z": -302,
    "y": 0
  },
  {
    "pos": 375,
    "z": -302,
    "y": 4
  },
  {
    "pos": 376,
    "z": 669,
    "y": 982
  },
  {
    "pos": 377,
    "z": 619,
    "y": 914
  },
  {
    "pos": 378,
    "z": 610,
    "y": 878
  },
  {
    "pos": 379,
    "z": 629,
    "y": 873
  },
  {
    "pos": 380,
    "z": 628,
    "y": 712
  },
  {
    "pos": 381,
    "z": 588,
    "y": 649
  },
  {
    "pos": 382,
    "z": 656,
    "y": 577
  },
  {
    "pos": 383,
    "z": 653,
    "y": 544
  },
  {
    "pos": 384,
    "z": 569,
    "y": 605
  },
  {
    "pos": 385,
    "z": -300,
    "y": 0
  },
  {
    "pos": 386,
    "z": -300,
    "y": 3
  },
  {
    "pos": 387,
    "z": 574,
    "y": 709
  },
  {
    "pos": 388,
    "z": -300,
    "y": 3
  },
  {
    "pos": 389,
    "z": -300,
    "y": 2
  },
  {
    "pos": 390,
    "z": 542,
    "y": 836
  },
  {
    "pos": 391,
    "z": -299,
    "y": 0
  },
  {
    "pos": 392,
    "z": -300,
    "y": 2
  },
  {
    "pos": 393,
    "z": -299,
    "y": 1
  },
  {
    "pos": 394,
    "z": 637,
    "y": 1012
  },
  {
    "pos": 395,
    "z": 688,
    "y": 976
  },
  {
    "pos": 396,
    "z": 688,
    "y": 952
  },
  {
    "pos": 397,
    "z": 744,
    "y": 843
  },
  {
    "pos": 398,
    "z": 732,
    "y": 855
  },
  {
    "pos": 399,
    "z": 684,
    "y": 704
  },
  {
    "pos": 400,
    "z": 735,
    "y": 551
  },
  {
    "pos": 401,
    "z": 668,
    "y": 531
  },
  {
    "pos": 402,
    "z": -303,
    "y": 27
  },
  {
    "pos": 403,
    "z": -302,
    "y": 4
  },
  {
    "pos": 404,
    "z": -303,
    "y": 28
  },
  {
    "pos": 405,
    "z": -301,
    "y": 1
  },
  {
    "pos": 406,
    "z": -303,
    "y": 6
  },
  {
    "pos": 407,
    "z": -302,
    "y": 0
  },
  {
    "pos": 408,
    "z": -303,
    "y": 4
  },
  {
    "pos": 409,
    "z": 642,
    "y": 886
  },
  {
    "pos": 410,
    "z": 652,
    "y": 913
  },
  {
    "pos": 411,
    "z": 680,
    "y": 941
  },
  {
    "pos": 412,
    "z": 751,
    "y": 941
  },
  {
    "pos": 413,
    "z": 748,
    "y": 894
  },
  {
    "pos": 414,
    "z": 739,
    "y": 885
  },
  {
    "pos": 415,
    "z": 795,
    "y": 714
  },
  {
    "pos": 416,
    "z": 771,
    "y": 655
  },
  {
    "pos": 417,
    "z": 750,
    "y": 640
  },
  {
    "pos": 418,
    "z": 715,
    "y": 551
  },
  {
    "pos": 419,
    "z": -303,
    "y": 3
  },
  {
    "pos": 420,
    "z": -303,
    "y": 2
  },
  {
    "pos": 421,
    "z": -304,
    "y": 4
  },
  {
    "pos": 422,
    "z": 608,
    "y": 731
  },
  {
    "pos": 423,
    "z": -304,
    "y": 8
  },
  {
    "pos": 424,
    "z": -305,
    "y": 7
  },
  {
    "pos": 425,
    "z": -305,
    "y": 3
  },
  {
    "pos": 426,
    "z": 721,
    "y": 960
  },
  {
    "pos": 427,
    "z": -306,
    "y": 5
  },
  {
    "pos": 428,
    "z": 797,
    "y": 875
  },
  {
    "pos": 429,
    "z": 824,
    "y": 767
  },
  {
    "pos": 430,
    "z": 769,
    "y": 706
  },
  {
    "pos": 431,
    "z": 760,
    "y": 701
  },
  {
    "pos": 432,
    "z": 712,
    "y": 606
  },
  {
    "pos": 433,
    "z": -310,
    "y": 2
  },
  {
    "pos": 437,
    "z": 751,
    "y": 820
  },
  {
    "pos": 440,
    "z": 806,
    "y": 952
  },
  {
    "pos": 441,
    "z": 821,
    "y": 922
  },
  {
    "pos": 442,
    "z": 823,
    "y": 880
  },
  {
    "pos": 443,
    "z": 859,
    "y": 833
  },
  {
    "pos": 444,
    "z": 953,
    "y": 772
  },
  {
    "pos": 445,
    "z": 858,
    "y": 691
  },
  {
    "pos": 446,
    "z": 826,
    "y": 622
  },
  {
    "pos": 447,
    "z": 862,
    "y": 565
  },
  {
    "pos": 448,
    "z": 807,
    "y": 596
  },
  {
    "pos": 449,
    "z": 836,
    "y": 586
  },
  {
    "pos": 451,
    "z": 797,
    "y": 792
  },
  {
    "pos": 453,
    "z": 830,
    "y": 897
  },
  {
    "pos": 454,
    "z": 871,
    "y": 903
  },
  {
    "pos": 455,
    "z": 1011,
    "y": 852
  },
  {
    "pos": 456,
    "z": 993,
    "y": 874
  },
  {
    "pos": 457,
    "z": 994,
    "y": 803
  },
  {
    "pos": 458,
    "z": 1022,
    "y": 664
  },
  {
    "pos": 459,
    "z": 915,
    "y": 777
  },
  {
    "pos": 460,
    "z": 904,
    "y": 649
  },
  {
    "pos": 461,
    "z": 904,
    "y": 645
  },
  {
    "pos": 465,
    "z": 890,
    "y": 842
  },
  {
    "pos": 467,
    "z": 914,
    "y": 882
  },
  {
    "pos": 468,
    "z": 905,
    "y": 882
  },
  {
    "pos": 470,
    "z": 1018,
    "y": 763
  },
  {
    "pos": 471,
    "z": 998,
    "y": 677
  },
  {
    "pos": 472,
    "z": 976,
    "y": 585
  },
  {
    "pos": 478,
    "z": 987,
    "y": 812
  },
  {
    "pos": 479,
    "z": 1132,
    "y": 921
  },
  {
    "pos": 480,
    "z": 1083,
    "y": 802
  },
  {
    "pos": 481,
    "z": 1143,
    "y": 707
  },
  {
    "pos": 482,
    "z": 1125,
    "y": 768
  },
  {
    "pos": 483,
    "z": 1111,
    "y": 704
  },
  {
    "pos": 484,
    "z": 1149,
    "y": 683
  },
  {
    "pos": 485,
    "z": 1056,
    "y": 611
  },
  {
    "pos": 489,
    "z": 1045,
    "y": 822
  },
  {
    "pos": 490,
    "z": 1115,
    "y": 835
  },
  {
    "pos": 491,
    "z": 1158,
    "y": 842
  },
  {
    "pos": 492,
    "z": 1183,
    "y": 857
  },
  {
    "pos": 493,
    "z": 1167,
    "y": 709
  },
  {
    "pos": 494,
    "z": 1180,
    "y": 637
  },
  {
    "pos": 495,
    "z": 1177,
    "y": 654
  },
  {
    "pos": 498,
    "z": 1046,
    "y": 820
  },
  {
    "pos": 499,
    "z": 1193,
    "y": 892
  }
]